Metadata-Version: 2.1
Name: daniel_fav_distributions
Version: 1.0
Summary: Gaussian and Binomial distributions
Author: Daniel de la Riva Massaad
Author-email: danieldelariva97@gmail.com
